Metadata-Version: 1.1
Name: intting
Version: 0.2.0
Summary: easy to user int (beta)
Home-page: https://pypi.org
Author: zjy_090820
Author-email: a1234567890001919@outlook.com
License: UNKNOWN
Platform: UNKNOWN
Classifier: Programming Language :: Python :: 3
Classifier: License :: OSI Approved :: MIT License
Classifier: Operating System :: OS Independent
